[
    {
        "key": "dbln",
        "value": "%7B%2261565717680711%22%3A%22m7XEAHEA%22%2C%2261566858825146%22%3A%22Rhf8hyh6%22%7D",
        "domain": "facebook.com",
        "path": "/login/device-based/",
        "hostOnly": false,
        "creation": "2024-10-16T10:05:24.338Z",
        "lastAccessed": "2024-10-16T10:05:24.339Z"
    },
    {
        "key": "sb",
        "value": "E53qZsrbiMwi5TnlgP_bzXdw",
        "domain": "facebook.com",
        "path": "/",
        "hostOnly": false,
        "creation": "2024-10-16T10:05:24.339Z",
        "lastAccessed": "2024-10-16T10:05:24.339Z"
    },
    {
        "key": "vpd",
        "value": "v1%3B783x393x2.75",
        "domain": "facebook.com",
        "path": "/",
        "hostOnly": false,
        "creation": "2024-10-16T10:05:24.339Z",
        "lastAccessed": "2024-10-16T10:05:24.339Z"
    },
    {
        "key": "dpr",
        "value": "3.0234789848327637",
        "domain": "facebook.com",
        "path": "/",
        "hostOnly": false,
        "creation": "2024-10-16T10:05:24.339Z",
        "lastAccessed": "2024-10-16T10:05:24.339Z"
    },
    {
        "key": "ps_l",
        "value": "1",
        "domain": "facebook.com",
        "path": "/",
        "hostOnly": false,
        "creation": "2024-10-16T10:05:24.339Z",
        "lastAccessed": "2024-10-16T10:05:24.339Z"
    },
    {
        "key": "ps_n",
        "value": "1",
        "domain": "facebook.com",
        "path": "/",
        "hostOnly": false,
        "creation": "2024-10-16T10:05:24.339Z",
        "lastAccessed": "2024-10-16T10:05:24.339Z"
    },
    {
        "key": "datr",
        "value": "VcIGZ8Iqe4bJh_bIiOG1F5bi",
        "domain": "facebook.com",
        "path": "/",
        "hostOnly": false,
        "creation": "2024-10-16T10:05:24.339Z",
        "lastAccessed": "2024-10-16T10:05:24.339Z"
    },
    {
        "key": "locale",
        "value": "en_GB",
        "domain": "facebook.com",
        "path": "/",
        "hostOnly": false,
        "creation": "2024-10-16T10:05:24.339Z",
        "lastAccessed": "2024-10-16T10:05:24.339Z"
    },
    {
        "key": "wd",
        "value": "393x783",
        "domain": "facebook.com",
        "path": "/",
        "hostOnly": false,
        "creation": "2024-10-16T10:05:24.339Z",
        "lastAccessed": "2024-10-16T10:05:24.339Z"
    },
    {
        "key": "c_user",
        "value": "61566858825146",
        "domain": "facebook.com",
        "path": "/",
        "hostOnly": false,
        "creation": "2024-10-16T10:05:24.339Z",
        "lastAccessed": "2024-10-16T10:05:24.339Z"
    },
    {
        "key": "xs",
        "value": "25%3AWOjXm0ZnZn0P-g%3A2%3A1729072734%3A-1%3A-1",
        "domain": "facebook.com",
        "path": "/",
        "hostOnly": false,
        "creation": "2024-10-16T10:05:24.339Z",
        "lastAccessed": "2024-10-16T10:05:24.339Z"
    },
    {
        "key": "fr",
        "value": "1N1wLQ2C30BIGoNeD.AWVBcfJ4cNUlXBAuu6_uw1QvZfw.BnD4Gn..AAA.0.0.BnD45g.AWUaN_xt5Jg",
        "domain": "facebook.com",
        "path": "/",
        "hostOnly": false,
        "creation": "2024-10-16T10:05:24.339Z",
        "lastAccessed": "2024-10-16T10:05:24.339Z"
    },
    {
        "key": "fbl_st",
        "value": "100434187%3BT%3A28817882",
        "domain": "facebook.com",
        "path": "/",
        "hostOnly": false,
        "creation": "2024-10-16T10:05:24.339Z",
        "lastAccessed": "2024-10-16T10:05:24.339Z"
    },
    {
        "key": "wl_cbv",
        "value": "v2%3Bclient_version%3A2649%3Btimestamp%3A1729072738",
        "domain": "facebook.com",
        "path": "/",
        "hostOnly": false,
        "creation": "2024-10-16T10:05:24.339Z",
        "lastAccessed": "2024-10-16T10:05:24.339Z"
    }
]
